{
  "info": {
    "_postman_id": "a1b2c3d4-6720-4000-8000-000000000000",
    "name": "Subjects",
    "description": "Subject catalogue, enrolment, members, top contributors, published question sets, leaderboard.",
    "schema": "https://schema.getpostman.com/json/collection/v2.1.0/collection.json"
  },
  "item": [
    {
      "name": "List Subjects",
      "request": {
        "method": "GET",
        "header": [],
        "url": {
          "raw": "{{base_url}}/subjects",
          "host": [
            "{{base_url}}"
          ],
          "path": [
            "subjects"
          ],
          "query": [
            {
              "key": "college",
              "value": "",
              "description": "",
              "disabled": true
            },
            {
              "key": "academic_year",
              "value": "0",
              "description": "",
              "disabled": true
            },
            {
              "key": "page",
              "value": "1",
              "description": "",
              "disabled": true
            },
            {
              "key": "size",
              "value": "20",
              "description": "",
              "disabled": true
            }
          ]
        },
        "description": "**List Subjects**\n\n`operationId`: `subjects_list`\n\n**Response schema:** `SubjectListResponse`"
      },
      "response": []
    },
    {
      "name": "My Subjects",
      "request": {
        "method": "GET",
        "header": [],
        "url": {
          "raw": "{{base_url}}/subjects/me",
          "host": [
            "{{base_url}}"
          ],
          "path": [
            "subjects",
            "me"
          ],
          "query": [
            {
              "key": "page",
              "value": "1",
              "description": "",
              "disabled": true
            },
            {
              "key": "size",
              "value": "20",
              "description": "",
              "disabled": true
            }
          ]
        },
        "description": "**My Subjects**\n\n`operationId`: `subjects_list_mine`\n\n**Requires:** Bearer token (`access_token`).\n\n**Response schema:** `SubjectListResponse`",
        "auth": {
          "type": "bearer",
          "bearer": [
            {
              "key": "token",
              "value": "{{access_token}}",
              "type": "string"
            }
          ]
        }
      },
      "response": []
    },
    {
      "name": "Get Subject",
      "request": {
        "method": "GET",
        "header": [],
        "url": {
          "raw": "{{base_url}}/subjects/:subject_id",
          "host": [
            "{{base_url}}"
          ],
          "path": [
            "subjects",
            ":subject_id"
          ],
          "variable": [
            {
              "key": "subject_id",
              "value": "{{subject_id}}",
              "description": "Path variable :subject_id"
            }
          ]
        },
        "description": "**Get Subject**\n\n`operationId`: `subjects_get`\n\n**Response schema:** `SubjectResponse`"
      },
      "response": []
    },
    {
      "name": "Unenroll",
      "request": {
        "method": "DELETE",
        "header": [],
        "url": {
          "raw": "{{base_url}}/subjects/:subject_id/enroll",
          "host": [
            "{{base_url}}"
          ],
          "path": [
            "subjects",
            ":subject_id",
            "enroll"
          ],
          "variable": [
            {
              "key": "subject_id",
              "value": "{{subject_id}}",
              "description": "Path variable :subject_id"
            }
          ]
        },
        "description": "**Unenroll**\n\n`operationId`: `subjects_unenroll`\n\n**Requires:** Bearer token (`access_token`).",
        "auth": {
          "type": "bearer",
          "bearer": [
            {
              "key": "token",
              "value": "{{access_token}}",
              "type": "string"
            }
          ]
        }
      },
      "response": []
    },
    {
      "name": "Enroll",
      "request": {
        "method": "POST",
        "header": [],
        "url": {
          "raw": "{{base_url}}/subjects/:subject_id/enroll",
          "host": [
            "{{base_url}}"
          ],
          "path": [
            "subjects",
            ":subject_id",
            "enroll"
          ],
          "variable": [
            {
              "key": "subject_id",
              "value": "{{subject_id}}",
              "description": "Path variable :subject_id"
            }
          ]
        },
        "description": "**Enroll**\n\n`operationId`: `subjects_enroll`\n\n**Requires:** Bearer token (`access_token`).\n\n**Response schema:** `EnrollmentResponse`",
        "auth": {
          "type": "bearer",
          "bearer": [
            {
              "key": "token",
              "value": "{{access_token}}",
              "type": "string"
            }
          ]
        }
      },
      "response": []
    },
    {
      "name": "Get Leaderboard",
      "request": {
        "method": "GET",
        "header": [],
        "url": {
          "raw": "{{base_url}}/subjects/:subject_id/leaderboard",
          "host": [
            "{{base_url}}"
          ],
          "path": [
            "subjects",
            ":subject_id",
            "leaderboard"
          ],
          "query": [
            {
              "key": "limit",
              "value": "10",
              "description": "",
              "disabled": true
            }
          ],
          "variable": [
            {
              "key": "subject_id",
              "value": "{{subject_id}}",
              "description": "Path variable :subject_id"
            }
          ]
        },
        "description": "**Get Leaderboard**\n\n`operationId`: `subjects_get_leaderboard`\n\n**Requires:** Bearer token (`access_token`).\n\n**Response schema:** `SubjectLeaderboardEntry[]`",
        "auth": {
          "type": "bearer",
          "bearer": [
            {
              "key": "token",
              "value": "{{access_token}}",
              "type": "string"
            }
          ]
        }
      },
      "response": []
    },
    {
      "name": "Get Members",
      "request": {
        "method": "GET",
        "header": [],
        "url": {
          "raw": "{{base_url}}/subjects/:subject_id/members",
          "host": [
            "{{base_url}}"
          ],
          "path": [
            "subjects",
            ":subject_id",
            "members"
          ],
          "query": [
            {
              "key": "page",
              "value": "1",
              "description": "",
              "disabled": true
            },
            {
              "key": "size",
              "value": "20",
              "description": "",
              "disabled": true
            }
          ],
          "variable": [
            {
              "key": "subject_id",
              "value": "{{subject_id}}",
              "description": "Path variable :subject_id"
            }
          ]
        },
        "description": "**Get Members**\n\n`operationId`: `subjects_get_members`\n\n**Response schema:** `SubjectMemberListResponse`"
      },
      "response": []
    },
    {
      "name": "Get Published Sets",
      "request": {
        "method": "GET",
        "header": [],
        "url": {
          "raw": "{{base_url}}/subjects/:subject_id/question-sets",
          "host": [
            "{{base_url}}"
          ],
          "path": [
            "subjects",
            ":subject_id",
            "question-sets"
          ],
          "query": [
            {
              "key": "page",
              "value": "1",
              "description": "",
              "disabled": true
            },
            {
              "key": "size",
              "value": "20",
              "description": "",
              "disabled": true
            }
          ],
          "variable": [
            {
              "key": "subject_id",
              "value": "{{subject_id}}",
              "description": "Path variable :subject_id"
            }
          ]
        },
        "description": "**Get Published Sets**\n\n`operationId`: `subjects_get_published_sets`\n\n**Response schema:** `SubjectPublishedSetListResponse`"
      },
      "response": []
    },
    {
      "name": "Get Top Contributors",
      "request": {
        "method": "GET",
        "header": [],
        "url": {
          "raw": "{{base_url}}/subjects/:subject_id/top-contributors",
          "host": [
            "{{base_url}}"
          ],
          "path": [
            "subjects",
            ":subject_id",
            "top-contributors"
          ],
          "query": [
            {
              "key": "limit",
              "value": "10",
              "description": "",
              "disabled": true
            }
          ],
          "variable": [
            {
              "key": "subject_id",
              "value": "{{subject_id}}",
              "description": "Path variable :subject_id"
            }
          ]
        },
        "description": "**Get Top Contributors**\n\n`operationId`: `subjects_get_top_contributors`\n\n**Response schema:** `SubjectContributorResponse[]`"
      },
      "response": []
    }
  ]
}
